hg38genome/__init__.py
hg38genome/core/__init__.py
hg38genome/core/calculate_bias.py
hg38genome/core/hg38_core.py
hg38genome/core/interval_utils.py
hg38genome/core/seq_utils.py
hg38genome/data/CDSs.parquet
hg38genome/data/JASPAR2022_pfm/MA0002.1.pfm
hg38genome/data/JASPAR2022_pfm/MA0003.1.pfm
hg38genome/data/JASPAR2022_pfm/MA0003.2.pfm
hg38genome/data/JASPAR2022_pfm/MA0003.3.pfm
hg38genome/data/JASPAR2022_pfm/MA0003.4.pfm
hg38genome/data/JASPAR2022_pfm/MA0007.2.pfm
hg38genome/data/JASPAR2022_pfm/MA0009.2.pfm
hg38genome/data/JASPAR2022_pfm/MA0014.2.pfm
hg38genome/data/JASPAR2022_pfm/MA0014.3.pfm
hg38genome/data/JASPAR2022_pfm/MA0017.1.pfm
hg38genome/data/JASPAR2022_pfm/MA0017.2.pfm
hg38genome/data/JASPAR2022_pfm/MA0018.1.pfm
hg38genome/data/JASPAR2022_pfm/MA0018.3.pfm
hg38genome/data/JASPAR2022_pfm/MA0018.4.pfm
hg38genome/data/JASPAR2022_pfm/MA0024.1.pfm
hg38genome/data/JASPAR2022_pfm/MA0024.2.pfm
hg38genome/data/JASPAR2022_pfm/MA0024.3.pfm
hg38genome/data/JASPAR2022_pfm/MA0025.1.pfm
hg38genome/data/JASPAR2022_pfm/MA0025.2.pfm
hg38genome/data/JASPAR2022_pfm/MA0027.2.pfm
hg38genome/data/JASPAR2022_pfm/MA0028.1.pfm
hg38genome/data/JASPAR2022_pfm/MA0028.2.pfm
hg38genome/data/JASPAR2022_pfm/MA0030.1.pfm
hg38genome/data/JASPAR2022_pfm/MA0031.1.pfm
hg38genome/data/JASPAR2022_pfm/MA0032.1.pfm
hg38genome/data/JASPAR2022_pfm/MA0032.2.pfm
hg38genome/data/JASPAR2022_pfm/MA0033.1.pfm
hg38genome/data/JASPAR2022_pfm/MA0033.2.pfm
hg38genome/data/JASPAR2022_pfm/MA0035.4.pfm
hg38genome/data/JASPAR2022_pfm/MA0036.1.pfm
hg38genome/data/JASPAR2022_pfm/MA0036.2.pfm
hg38genome/data/JASPAR2022_pfm/MA0036.3.pfm
hg38genome/data/JASPAR2022_pfm/MA0037.1.pfm
hg38genome/data/JASPAR2022_pfm/MA0037.2.pfm
hg38genome/data/JASPAR2022_pfm/MA0037.3.pfm
hg38genome/data/JASPAR2022_pfm/MA0038.2.pfm
hg38genome/data/JASPAR2022_pfm/MA0039.3.pfm
hg38genome/data/JASPAR2022_pfm/MA0039.4.pfm
hg38genome/data/JASPAR2022_pfm/MA0041.2.pfm
hg38genome/data/JASPAR2022_pfm/MA0042.1.pfm
hg38genome-1.0.1.dist-info/LICENSE.md
hg38genome-1.0.1.dist-info/METADATA
hg38genome-1.0.1.dist-info/WHEEL
hg38genome-1.0.1.dist-info/RECORD
